<?xml version="1.0" encoding="utf-8"?><Book><Page><Stroke duration="360" startSecond="1439091603" startMillisecond="673" lineWidth="1"><Packet x="554.375" y="185" pressure="0" deltaTime="0" /><Packet x="554.25" y="185" pressure="106" deltaTime="13" /><Packet x="554.25" y="185.125" pressure="112" deltaTime="13" /><Packet x="555.625" y="185.625" pressure="118" deltaTime="40" /><Packet x="562.75" y="184.75" pressure="122" deltaTime="54" /><Packet x="585.875" y="176.625" pressure="122" deltaTime="93" /><Packet x="586.125" y="176.25" pressure="122" deltaTime="40" /><Packet x="584.5" y="175.75" pressure="122" deltaTime="67" /><Packet x="583" y="175.375" pressure="120" deltaTime="13" /><Packet x="580.875" y="175.25" pressure="116" deltaTime="13" /><Packet x="577.75" y="175" pressure="0" deltaTime="14" /></Stroke><Stroke duration="373" startSecond="1439091604" startMillisecond="161" lineWidth="1"><Packet x="574.625" y="167.75" pressure="78" deltaTime="0" /><Packet x="575.125" y="167.5" pressure="112" deltaTime="40" /><Packet x="574.75" y="168" pressure="116" deltaTime="26" /><Packet x="571" y="179" pressure="120" deltaTime="107" /><Packet x="567.875" y="186.375" pressure="120" deltaTime="27" /><Packet x="561.125" y="199.125" pressure="122" deltaTime="40" /><Packet x="558.5" y="203.125" pressure="122" deltaTime="13" /><Packet x="555.875" y="206.125" pressure="122" deltaTime="13" /><Packet x="552" y="209.375" pressure="122" deltaTime="27" /><Packet x="550.875" y="209.625" pressure="122" deltaTime="13" /><Packet x="550.375" y="209" pressure="122" deltaTime="27" /><Packet x="550.375" y="208.125" pressure="120" deltaTime="13" /><Packet x="551.375" y="206.5" pressure="116" deltaTime="14" /><Packet x="552.875" y="204.625" pressure="60" deltaTime="13" /></Stroke><Stroke duration="3133" startSecond="1439091604" startMillisecond="684" lineWidth="1"><Packet x="567" y="194.375" pressure="0" deltaTime="0" /><Packet x="569.375" y="193.875" pressure="70" deltaTime="13" /><Packet x="572.125" y="193.375" pressure="96" deltaTime="13" /><Packet x="575.25" y="193" pressure="106" deltaTime="14" /><Packet x="581.375" y="192.75" pressure="114" deltaTime="26" /><Packet x="588" y="193" pressure="118" deltaTime="40" /><Packet x="589.25" y="193.375" pressure="120" deltaTime="14" /><Packet x="591.5" y="194.5" pressure="122" deltaTime="93" /><Packet x="589.875" y="194.25" pressure="122" deltaTime="107" /><Packet x="588.625" y="194.625" pressure="122" deltaTime="13" /><Packet x="581.125" y="198.125" pressure="118" deltaTime="53" /><Packet x="569.75" y="204.375" pressure="106" deltaTime="54" /><Packet x="554" y="218.375" pressure="116" deltaTime="120" /><Packet x="555.375" y="218.75" pressure="120" deltaTime="106" /><Packet x="557.25" y="218.125" pressure="120" deltaTime="40" /><Packet x="561.125" y="215.625" pressure="120" deltaTime="67" /><Packet x="576.125" y="209.5" pressure="120" deltaTime="53" /><Packet x="582.5" y="207.75" pressure="120" deltaTime="27" /><Packet x="585.625" y="207.5" pressure="120" deltaTime="40" /><Packet x="583.25" y="207.625" pressure="122" deltaTime="67" /><Packet x="581.25" y="207.625" pressure="120" deltaTime="26" /><Packet x="577.75" y="206.875" pressure="104" deltaTime="40" /><Packet x="576" y="205.75" pressure="100" deltaTime="27" /><Packet x="574.75" y="205" pressure="104" deltaTime="40" /><Packet x="576.25" y="203.125" pressure="116" deltaTime="93" /><Packet x="576.625" y="218.375" pressure="122" deltaTime="414" /><Packet x="575.875" y="224.25" pressure="122" deltaTime="120" /><Packet x="576.25" y="228.125" pressure="124" deltaTime="80" /><Packet x="576.125" y="229" pressure="124" deltaTime="13" /><Packet x="574.875" y="237.375" pressure="124" deltaTime="360" /><Packet x="572.25" y="237" pressure="124" deltaTime="187" /><Packet x="568" y="233.875" pressure="124" deltaTime="80" /><Packet x="564.25" y="229.75" pressure="122" deltaTime="53" /><Packet x="559.5" y="226.125" pressure="122" deltaTime="67" /><Packet x="558.75" y="223.875" pressure="122" deltaTime="80" /><Packet x="559.375" y="222.625" pressure="122" deltaTime="106" /><Packet x="560.625" y="222.125" pressure="122" deltaTime="40" /><Packet x="563.375" y="221.75" pressure="122" deltaTime="40" /><Packet x="566.875" y="222.375" pressure="122" deltaTime="94" /><Packet x="568.25" y="223.5" pressure="124" deltaTime="133" /><Packet x="552.5" y="236.125" pressure="118" deltaTime="80" /></Stroke></Page></Book>