<?xml version="1.0" encoding="utf-8"?><Book><Page><Stroke duration="120" startSecond="1438997726" startMillisecond="174" lineWidth="1"><Packet x="481.5" y="406" pressure="0" deltaTime="0" /><Packet x="482.125" y="406.375" pressure="94" deltaTime="13" /><Packet x="482.75" y="407.25" pressure="100" deltaTime="13" /><Packet x="484" y="410.625" pressure="112" deltaTime="54" /><Packet x="483.75" y="411.75" pressure="106" deltaTime="26" /><Packet x="482.875" y="412.625" pressure="46" deltaTime="14" /></Stroke><Stroke duration="2346" startSecond="1438997726" startMillisecond="410" lineWidth="1"><Packet x="474.625" y="419.625" pressure="0" deltaTime="0" /><Packet x="474.5" y="419.75" pressure="86" deltaTime="13" /><Packet x="473" y="420.875" pressure="110" deltaTime="40" /><Packet x="469.75" y="424.875" pressure="114" deltaTime="27" /><Packet x="467.625" y="427.375" pressure="114" deltaTime="13" /><Packet x="462.5" y="434.375" pressure="116" deltaTime="40" /><Packet x="460.25" y="436.25" pressure="116" deltaTime="40" /><Packet x="459.125" y="436.5" pressure="118" deltaTime="80" /><Packet x="460.125" y="434.75" pressure="116" deltaTime="80" /><Packet x="466.375" y="430.75" pressure="112" deltaTime="53" /><Packet x="474.625" y="426.625" pressure="110" deltaTime="27" /><Packet x="489.75" y="421.5" pressure="106" deltaTime="40" /><Packet x="495.125" y="420.875" pressure="108" deltaTime="27" /><Packet x="496" y="421.125" pressure="110" deltaTime="13" /><Packet x="496.25" y="421.75" pressure="110" deltaTime="27" /><Packet x="492.625" y="425.375" pressure="116" deltaTime="80" /><Packet x="491.5" y="426" pressure="116" deltaTime="13" /><Packet x="490" y="426.625" pressure="116" deltaTime="13" /><Packet x="475" y="433.5" pressure="76" deltaTime="67" /><Packet x="473.5" y="434.25" pressure="80" deltaTime="13" /><Packet x="472.875" y="435.25" pressure="92" deltaTime="40" /><Packet x="473.5" y="435.625" pressure="112" deltaTime="107" /><Packet x="479.5" y="435.75" pressure="114" deltaTime="53" /><Packet x="483.125" y="436.25" pressure="114" deltaTime="54" /><Packet x="475.375" y="439.875" pressure="106" deltaTime="66" /><Packet x="472.625" y="441.75" pressure="108" deltaTime="27" /><Packet x="472.125" y="442.625" pressure="110" deltaTime="40" /><Packet x="478.75" y="441.75" pressure="116" deltaTime="93" /><Packet x="480.625" y="442" pressure="116" deltaTime="27" /><Packet x="481" y="442.5" pressure="116" deltaTime="27" /><Packet x="478.375" y="445.25" pressure="116" deltaTime="40" /><Packet x="471.375" y="450" pressure="114" deltaTime="40" /><Packet x="466.625" y="454.125" pressure="118" deltaTime="200" /><Packet x="488.875" y="444.5" pressure="118" deltaTime="133" /><Packet x="492.875" y="443.25" pressure="118" deltaTime="40" /><Packet x="493.125" y="443.125" pressure="118" deltaTime="13" /><Packet x="489.875" y="441.125" pressure="118" deltaTime="94" /><Packet x="487.875" y="439" pressure="116" deltaTime="26" /><Packet x="485.625" y="432.75" pressure="110" deltaTime="67" /><Packet x="484.875" y="431.875" pressure="112" deltaTime="53" /><Packet x="485.125" y="434.125" pressure="114" deltaTime="94" /><Packet x="484.75" y="435.75" pressure="116" deltaTime="26" /><Packet x="479.25" y="453.25" pressure="116" deltaTime="107" /><Packet x="477.875" y="456.375" pressure="116" deltaTime="13" /><Packet x="472.625" y="464" pressure="118" deltaTime="40" /><Packet x="470.75" y="465.75" pressure="118" deltaTime="14" /><Packet x="465.25" y="469.5" pressure="118" deltaTime="40" /><Packet x="464.25" y="469.5" pressure="116" deltaTime="26" /><Packet x="465.125" y="468.125" pressure="114" deltaTime="14" /><Packet x="466.375" y="465.75" pressure="102" deltaTime="13" /><Packet x="468.5" y="462.125" pressure="0" deltaTime="13" /></Stroke><Stroke duration="226" startSecond="1438997729" startMillisecond="31" lineWidth="1"><Packet x="486.125" y="455.75" pressure="0" deltaTime="0" /><Packet x="486.75" y="455.875" pressure="90" deltaTime="13" /><Packet x="488.625" y="457.375" pressure="106" deltaTime="27" /><Packet x="489.75" y="458.5" pressure="110" deltaTime="13" /><Packet x="490.875" y="459.75" pressure="112" deltaTime="13" /><Packet x="496" y="466.75" pressure="116" deltaTime="67" /><Packet x="496.25" y="467.5" pressure="118" deltaTime="27" /><Packet x="495.125" y="467.125" pressure="118" deltaTime="40" /><Packet x="493.75" y="466.5" pressure="116" deltaTime="13" /><Packet x="491.875" y="465" pressure="60" deltaTime="13" /></Stroke></Page></Book>