<?xml version="1.0" encoding="utf-8"?><Book><Page><Stroke duration="3893" startSecond="1439091675" startMillisecond="506" lineWidth="1"><Packet x="203.875" y="531.75" pressure="114" deltaTime="0" /><Packet x="196.25" y="551.875" pressure="120" deltaTime="80" /><Packet x="196" y="554.375" pressure="122" deltaTime="26" /><Packet x="199" y="552.625" pressure="122" deltaTime="54" /><Packet x="209" y="544.875" pressure="120" deltaTime="40" /><Packet x="221" y="538.375" pressure="120" deltaTime="66" /><Packet x="219.5" y="538.25" pressure="122" deltaTime="54" /><Packet x="216.25" y="540" pressure="120" deltaTime="66" /><Packet x="213" y="543.875" pressure="120" deltaTime="80" /><Packet x="211.375" y="547.625" pressure="120" deltaTime="27" /><Packet x="208" y="560.375" pressure="122" deltaTime="53" /><Packet x="207.375" y="564.625" pressure="122" deltaTime="14" /><Packet x="206.625" y="573.125" pressure="122" deltaTime="26" /><Packet x="206.625" y="579.625" pressure="122" deltaTime="27" /><Packet x="207.25" y="583.375" pressure="124" deltaTime="93" /><Packet x="210.125" y="569.875" pressure="120" deltaTime="94" /><Packet x="211.5" y="559.5" pressure="116" deltaTime="40" /><Packet x="213.125" y="556.5" pressure="116" deltaTime="26" /><Packet x="216.25" y="554.25" pressure="120" deltaTime="54" /><Packet x="219.125" y="554.75" pressure="120" deltaTime="40" /><Packet x="220" y="555.5" pressure="122" deltaTime="26" /><Packet x="215.75" y="562.5" pressure="122" deltaTime="107" /><Packet x="214.5" y="566.25" pressure="122" deltaTime="53" /><Packet x="215.375" y="568.125" pressure="122" deltaTime="67" /><Packet x="221.75" y="568.875" pressure="122" deltaTime="133" /><Packet x="220.5" y="569.125" pressure="122" deltaTime="94" /><Packet x="217.875" y="571.25" pressure="122" deltaTime="40" /><Packet x="204" y="585" pressure="122" deltaTime="93" /><Packet x="196.375" y="591.875" pressure="122" deltaTime="27" /><Packet x="190.875" y="597.875" pressure="124" deltaTime="66" /><Packet x="192.75" y="595.5" pressure="122" deltaTime="80" /><Packet x="193.25" y="594.875" pressure="122" deltaTime="14" /><Packet x="196.5" y="590.125" pressure="122" deltaTime="80" /><Packet x="198.125" y="588.75" pressure="122" deltaTime="26" /><Packet x="201.375" y="587.75" pressure="124" deltaTime="134" /><Packet x="202.625" y="588.25" pressure="124" deltaTime="213" /><Packet x="208.25" y="593.125" pressure="124" deltaTime="173" /><Packet x="211.5" y="594.375" pressure="124" deltaTime="67" /><Packet x="224.75" y="596" pressure="124" deltaTime="160" /><Packet x="229.375" y="594.75" pressure="124" deltaTime="173" /><Packet x="228.625" y="591" pressure="124" deltaTime="94" /><Packet x="226.5" y="588.25" pressure="124" deltaTime="26" /><Packet x="213.125" y="580.25" pressure="122" deltaTime="120" /><Packet x="216.875" y="585.625" pressure="124" deltaTime="160" /><Packet x="218.375" y="586.625" pressure="124" deltaTime="67" /><Packet x="228.75" y="579.75" pressure="120" deltaTime="120" /><Packet x="233.25" y="578.25" pressure="122" deltaTime="40" /><Packet x="235" y="578.375" pressure="122" deltaTime="40" /><Packet x="235.125" y="578.625" pressure="122" deltaTime="13" /><Packet x="236.25" y="581.375" pressure="124" deltaTime="174" /><Packet x="236.125" y="582.25" pressure="124" deltaTime="160" /><Packet x="233.75" y="580" pressure="120" deltaTime="80" /><Packet x="232.75" y="578.625" pressure="54" deltaTime="13" /></Stroke></Page></Book>