<?xml version="1.0" encoding="utf-8"?><Book><Page><Stroke duration="1586" startSecond="1439088732" startMillisecond="214" lineWidth="1"><Packet x="455.125" y="673.75" pressure="0" deltaTime="0" /><Packet x="454.875" y="674.5" pressure="88" deltaTime="13" /><Packet x="454.875" y="675.25" pressure="104" deltaTime="13" /><Packet x="456.125" y="676.625" pressure="120" deltaTime="67" /><Packet x="456.5" y="677.25" pressure="120" deltaTime="27" /><Packet x="457.75" y="677.625" pressure="120" deltaTime="40" /><Packet x="458.625" y="677.375" pressure="120" deltaTime="13" /><Packet x="470.125" y="672" pressure="122" deltaTime="67" /><Packet x="475.375" y="670.625" pressure="122" deltaTime="40" /><Packet x="478.875" y="668.625" pressure="122" deltaTime="26" /><Packet x="480" y="667.75" pressure="122" deltaTime="14" /><Packet x="480.375" y="666.75" pressure="122" deltaTime="26" /><Packet x="479.25" y="666.25" pressure="122" deltaTime="40" /><Packet x="477" y="666.5" pressure="120" deltaTime="27" /><Packet x="475.5" y="665.25" pressure="118" deltaTime="53" /><Packet x="473.5" y="659.25" pressure="116" deltaTime="107" /><Packet x="472.25" y="660" pressure="118" deltaTime="120" /><Packet x="470.125" y="664.875" pressure="120" deltaTime="107" /><Packet x="466.5" y="690.75" pressure="122" deltaTime="160" /><Packet x="465.25" y="705.25" pressure="122" deltaTime="53" /><Packet x="465.75" y="713.5" pressure="122" deltaTime="53" /><Packet x="465.5" y="715.5" pressure="122" deltaTime="27" /><Packet x="464.75" y="716.5" pressure="122" deltaTime="40" /><Packet x="462.125" y="711.75" pressure="122" deltaTime="107" /><Packet x="459.625" y="709.375" pressure="122" deltaTime="26" /><Packet x="453.625" y="706.25" pressure="122" deltaTime="54" /><Packet x="451.625" y="703.625" pressure="122" deltaTime="106" /><Packet x="456.125" y="700.375" pressure="122" deltaTime="94" /><Packet x="466.75" y="689.25" pressure="122" deltaTime="40" /><Packet x="471.875" y="683.25" pressure="120" deltaTime="13" /><Packet x="477.125" y="676.375" pressure="80" deltaTime="13" /></Stroke><Stroke duration="200" startSecond="1439088734" startMillisecond="64" lineWidth="1"><Packet x="490.375" y="651.875" pressure="0" deltaTime="0" /><Packet x="490.625" y="651.5" pressure="86" deltaTime="13" /><Packet x="490.875" y="651.5" pressure="104" deltaTime="13" /><Packet x="492.5" y="654.875" pressure="118" deltaTime="67" /><Packet x="493.5" y="657.25" pressure="120" deltaTime="53" /><Packet x="491.75" y="659.75" pressure="114" deltaTime="27" /><Packet x="490" y="661.5" pressure="100" deltaTime="13" /><Packet x="487.75" y="663.375" pressure="22" deltaTime="14" /></Stroke><Stroke duration="4346" startSecond="1439088734" startMillisecond="330" lineWidth="1"><Packet x="481.125" y="670.875" pressure="0" deltaTime="0" /><Packet x="480.625" y="671.625" pressure="86" deltaTime="13" /><Packet x="480" y="672.375" pressure="106" deltaTime="13" /><Packet x="478.125" y="674.625" pressure="118" deltaTime="54" /><Packet x="477.375" y="676.125" pressure="120" deltaTime="53" /><Packet x="478.125" y="676.125" pressure="120" deltaTime="93" /><Packet x="480" y="675.625" pressure="120" deltaTime="40" /><Packet x="492.875" y="669.25" pressure="120" deltaTime="80" /><Packet x="499.375" y="667.125" pressure="122" deltaTime="40" /><Packet x="501.75" y="666.875" pressure="122" deltaTime="94" /><Packet x="503.375" y="666" pressure="122" deltaTime="66" /><Packet x="496.875" y="669.375" pressure="120" deltaTime="147" /><Packet x="490.125" y="674.625" pressure="120" deltaTime="53" /><Packet x="486.875" y="678.125" pressure="120" deltaTime="27" /><Packet x="485.25" y="682.375" pressure="120" deltaTime="27" /><Packet x="485" y="686.375" pressure="122" deltaTime="40" /><Packet x="485.75" y="688.5" pressure="122" deltaTime="93" /><Packet x="485.25" y="685.625" pressure="120" deltaTime="80" /><Packet x="486.5" y="683.25" pressure="120" deltaTime="40" /><Packet x="493.125" y="678.5" pressure="120" deltaTime="53" /><Packet x="496.125" y="677.375" pressure="120" deltaTime="27" /><Packet x="498.625" y="678.25" pressure="122" deltaTime="107" /><Packet x="489.25" y="686.5" pressure="122" deltaTime="93" /><Packet x="488.375" y="687.75" pressure="122" deltaTime="40" /><Packet x="499.125" y="684.125" pressure="122" deltaTime="147" /><Packet x="484.25" y="692" pressure="98" deltaTime="120" /><Packet x="478.75" y="695.875" pressure="100" deltaTime="26" /><Packet x="476.375" y="698.125" pressure="106" deltaTime="27" /><Packet x="475.5" y="698.875" pressure="106" deltaTime="13" /><Packet x="473.75" y="701.375" pressure="114" deltaTime="67" /><Packet x="474.5" y="702.625" pressure="116" deltaTime="40" /><Packet x="474.75" y="703.125" pressure="118" deltaTime="13" /><Packet x="474.875" y="703.625" pressure="118" deltaTime="14" /><Packet x="474.875" y="704.125" pressure="118" deltaTime="13" /><Packet x="474.875" y="704.5" pressure="118" deltaTime="13" /><Packet x="475" y="705.5" pressure="118" deltaTime="14" /><Packet x="475.25" y="706.625" pressure="118" deltaTime="13" /><Packet x="476.875" y="709.875" pressure="120" deltaTime="40" /><Packet x="479.375" y="711.625" pressure="122" deltaTime="67" /><Packet x="478.5" y="710.375" pressure="120" deltaTime="80" /><Packet x="478.125" y="708" pressure="116" deltaTime="26" /><Packet x="477.625" y="704" pressure="100" deltaTime="40" /><Packet x="477.875" y="702.625" pressure="102" deltaTime="27" /><Packet x="483.75" y="698.25" pressure="114" deltaTime="120" /><Packet x="488.75" y="696.125" pressure="116" deltaTime="53" /><Packet x="497.5" y="693.875" pressure="118" deltaTime="67" /><Packet x="503.75" y="693" pressure="120" deltaTime="40" /><Packet x="509.25" y="693.625" pressure="122" deltaTime="320" /><Packet x="509" y="696.625" pressure="122" deltaTime="80" /><Packet x="505.75" y="707.625" pressure="122" deltaTime="80" /><Packet x="503.25" y="712.625" pressure="122" deltaTime="40" /><Packet x="499.75" y="717.75" pressure="122" deltaTime="107" /><Packet x="498.875" y="715.875" pressure="122" deltaTime="53" /><Packet x="497.5" y="714.375" pressure="122" deltaTime="27" /><Packet x="488.75" y="708.75" pressure="118" deltaTime="80" /><Packet x="484.25" y="702.5" pressure="116" deltaTime="93" /><Packet x="484" y="704.25" pressure="118" deltaTime="67" /><Packet x="484" y="704.875" pressure="118" deltaTime="13" /><Packet x="484.875" y="706.875" pressure="118" deltaTime="67" /><Packet x="485" y="709.875" pressure="120" deltaTime="66" /><Packet x="486.375" y="705.625" pressure="118" deltaTime="80" /><Packet x="488.25" y="702.5" pressure="116" deltaTime="40" /><Packet x="493.375" y="699.875" pressure="118" deltaTime="67" /><Packet x="496.875" y="699.125" pressure="120" deltaTime="80" /><Packet x="497.625" y="699.5" pressure="120" deltaTime="53" /><Packet x="497.125" y="700.875" pressure="120" deltaTime="40" /><Packet x="491" y="706.125" pressure="120" deltaTime="67" /><Packet x="489.5" y="708.75" pressure="120" deltaTime="107" /><Packet x="496.25" y="707" pressure="122" deltaTime="160" /><Packet x="493.75" y="707.5" pressure="122" deltaTime="80" /><Packet x="493.375" y="705.625" pressure="86" deltaTime="26" /></Stroke></Page></Book>