<?xml version="1.0" encoding="utf-8"?><Book><Page><Stroke duration="1400" startSecond="1439088347" startMillisecond="384" lineWidth="1"><Packet x="555.25" y="418.625" pressure="0" deltaTime="0" /><Packet x="555.125" y="418.875" pressure="98" deltaTime="13" /><Packet x="555.125" y="419.125" pressure="110" deltaTime="13" /><Packet x="556.125" y="420.75" pressure="118" deltaTime="40" /><Packet x="557.375" y="421.875" pressure="120" deltaTime="40" /><Packet x="558.375" y="422" pressure="120" deltaTime="27" /><Packet x="566.875" y="417.75" pressure="122" deltaTime="67" /><Packet x="573" y="416.375" pressure="122" deltaTime="66" /><Packet x="571.375" y="419.875" pressure="122" deltaTime="147" /><Packet x="552.875" y="443.25" pressure="122" deltaTime="173" /><Packet x="560.5" y="440.125" pressure="122" deltaTime="94" /><Packet x="570" y="435.5" pressure="122" deltaTime="66" /><Packet x="568.25" y="434.375" pressure="122" deltaTime="94" /><Packet x="567.25" y="430.25" pressure="120" deltaTime="146" /><Packet x="567.75" y="431.375" pressure="122" deltaTime="80" /><Packet x="568" y="436.375" pressure="122" deltaTime="107" /><Packet x="567.25" y="439.75" pressure="122" deltaTime="27" /><Packet x="562.25" y="451.375" pressure="122" deltaTime="53" /><Packet x="559.125" y="456.625" pressure="122" deltaTime="27" /><Packet x="557.625" y="458.375" pressure="122" deltaTime="13" /><Packet x="555" y="460.5" pressure="122" deltaTime="27" /><Packet x="553.75" y="460.75" pressure="124" deltaTime="13" /><Packet x="552.75" y="460.875" pressure="122" deltaTime="13" /><Packet x="552.25" y="460.125" pressure="122" deltaTime="14" /><Packet x="552.375" y="458.375" pressure="120" deltaTime="13" /><Packet x="553.875" y="454.875" pressure="118" deltaTime="13" /><Packet x="557.625" y="448.875" pressure="0" deltaTime="14" /></Stroke><Stroke duration="293" startSecond="1439088349" startMillisecond="34" lineWidth="1"><Packet x="577.5" y="431.125" pressure="0" deltaTime="0" /><Packet x="577.5" y="431.5" pressure="90" deltaTime="13" /><Packet x="577.625" y="432.75" pressure="112" deltaTime="27" /><Packet x="579.125" y="441.125" pressure="122" deltaTime="146" /><Packet x="580" y="437.375" pressure="122" deltaTime="54" /><Packet x="582.25" y="429.5" pressure="114" deltaTime="26" /><Packet x="584.125" y="422.25" pressure="0" deltaTime="27" /></Stroke><Stroke duration="866" startSecond="1439088349" startMillisecond="373" lineWidth="1"><Packet x="586.25" y="418" pressure="94" deltaTime="0" /><Packet x="588.125" y="414.75" pressure="118" deltaTime="93" /><Packet x="588.125" y="414.875" pressure="118" deltaTime="13" /><Packet x="587.75" y="417.75" pressure="120" deltaTime="187" /><Packet x="588.375" y="427.125" pressure="120" deltaTime="133" /><Packet x="587.5" y="437.375" pressure="122" deltaTime="94" /><Packet x="587.75" y="447.875" pressure="122" deltaTime="80" /><Packet x="588.5" y="455.5" pressure="122" deltaTime="66" /><Packet x="587.875" y="459" pressure="124" deltaTime="54" /><Packet x="586.75" y="457" pressure="124" deltaTime="93" /><Packet x="585.625" y="455.75" pressure="124" deltaTime="13" /><Packet x="583.625" y="454.125" pressure="122" deltaTime="14" /><Packet x="579.5" y="452.875" pressure="120" deltaTime="13" /><Packet x="573.25" y="452" pressure="56" deltaTime="13" /></Stroke><Stroke duration="1453" startSecond="1439088350" startMillisecond="821" lineWidth="1"><Packet x="553.625" y="465" pressure="112" deltaTime="0" /><Packet x="550.625" y="470.5" pressure="116" deltaTime="53" /><Packet x="546.25" y="476" pressure="122" deltaTime="107" /><Packet x="549.125" y="472.375" pressure="120" deltaTime="80" /><Packet x="553.375" y="469.25" pressure="120" deltaTime="53" /><Packet x="560" y="466.75" pressure="120" deltaTime="147" /><Packet x="563" y="466.625" pressure="120" deltaTime="53" /><Packet x="567.25" y="467.625" pressure="122" deltaTime="93" /><Packet x="570.875" y="469.25" pressure="122" deltaTime="80" /><Packet x="575.125" y="469.875" pressure="122" deltaTime="94" /><Packet x="576.875" y="469.625" pressure="122" deltaTime="66" /><Packet x="584.25" y="465" pressure="120" deltaTime="94" /><Packet x="586" y="464.875" pressure="120" deltaTime="40" /><Packet x="587.625" y="465.5" pressure="122" deltaTime="80" /><Packet x="591.125" y="469" pressure="122" deltaTime="120" /><Packet x="592.5" y="471.375" pressure="122" deltaTime="80" /><Packet x="591.875" y="471.875" pressure="124" deltaTime="160" /><Packet x="591.375" y="471.5" pressure="124" deltaTime="26" /><Packet x="590.375" y="470.25" pressure="122" deltaTime="14" /><Packet x="589.25" y="466.75" pressure="32" deltaTime="13" /></Stroke></Page></Book>