<?xml version="1.0" encoding="utf-8"?><Book><Page><Stroke duration="2093" startSecond="1439221927" startMillisecond="785" lineWidth="1"><Packet x="278.375" y="571.375" pressure="116" deltaTime="0" /><Packet x="278.875" y="572" pressure="118" deltaTime="13" /><Packet x="279.25" y="571.875" pressure="120" deltaTime="53" /><Packet x="278.875" y="570.125" pressure="118" deltaTime="40" /><Packet x="279.25" y="565.25" pressure="94" deltaTime="40" /><Packet x="280.875" y="562.375" pressure="86" deltaTime="54" /><Packet x="284.625" y="559.625" pressure="104" deltaTime="40" /><Packet x="289.25" y="557.375" pressure="112" deltaTime="26" /><Packet x="292.25" y="556.25" pressure="114" deltaTime="14" /><Packet x="299.125" y="553.875" pressure="118" deltaTime="80" /><Packet x="298.875" y="554.75" pressure="120" deltaTime="80" /><Packet x="298.625" y="555.125" pressure="120" deltaTime="13" /><Packet x="290" y="563.5" pressure="120" deltaTime="80" /><Packet x="291.375" y="556.125" pressure="120" deltaTime="387" /><Packet x="291" y="540.625" pressure="118" deltaTime="240" /><Packet x="289.875" y="558.125" pressure="120" deltaTime="133" /><Packet x="284.25" y="583" pressure="120" deltaTime="107" /><Packet x="292.625" y="573.625" pressure="118" deltaTime="333" /><Packet x="291.625" y="572.875" pressure="114" deltaTime="67" /><Packet x="294.375" y="578.75" pressure="120" deltaTime="200" /><Packet x="295.25" y="577" pressure="120" deltaTime="53" /><Packet x="298.5" y="571" pressure="88" deltaTime="27" /><Packet x="300.5" y="566.25" pressure="0" deltaTime="13" /></Stroke><Stroke duration="1266" startSecond="1439221930" startMillisecond="30" lineWidth="1"><Packet x="309.25" y="557" pressure="0" deltaTime="0" /><Packet x="309.625" y="557" pressure="84" deltaTime="13" /><Packet x="310.125" y="556.75" pressure="104" deltaTime="13" /><Packet x="313.125" y="556" pressure="116" deltaTime="67" /><Packet x="313.75" y="555.875" pressure="116" deltaTime="13" /><Packet x="320.875" y="553" pressure="118" deltaTime="67" /><Packet x="323.25" y="552.625" pressure="120" deltaTime="80" /><Packet x="322.375" y="552.375" pressure="118" deltaTime="53" /><Packet x="321.625" y="552.625" pressure="114" deltaTime="14" /><Packet x="318.625" y="554.25" pressure="74" deltaTime="40" /><Packet x="318.125" y="554.75" pressure="72" deltaTime="13" /><Packet x="316" y="558.125" pressure="108" deltaTime="93" /><Packet x="315.125" y="562.25" pressure="114" deltaTime="54" /><Packet x="315" y="568.375" pressure="118" deltaTime="66" /><Packet x="314.5" y="570.75" pressure="120" deltaTime="27" /><Packet x="314.25" y="571.5" pressure="120" deltaTime="13" /><Packet x="313.5" y="573.125" pressure="120" deltaTime="27" /><Packet x="312.125" y="574.875" pressure="120" deltaTime="27" /><Packet x="309.75" y="576.5" pressure="120" deltaTime="26" /><Packet x="304.625" y="578.75" pressure="120" deltaTime="40" /><Packet x="302.625" y="578.875" pressure="120" deltaTime="27" /><Packet x="301.375" y="578.25" pressure="120" deltaTime="93" /><Packet x="312.5" y="575" pressure="122" deltaTime="160" /><Packet x="326.875" y="572.875" pressure="122" deltaTime="54" /><Packet x="332.25" y="573.375" pressure="122" deltaTime="66" /><Packet x="328.875" y="572.625" pressure="122" deltaTime="94" /><Packet x="324.625" y="572.75" pressure="96" deltaTime="26" /></Stroke></Page></Book>