<?xml version="1.0" encoding="utf-8"?><Book><Page><Stroke duration="1813" startSecond="1439305792" startMillisecond="930" lineWidth="1"><Packet x="181.125" y="191.25" pressure="0" deltaTime="0" /><Packet x="182.75" y="192.25" pressure="114" deltaTime="53" /><Packet x="183.75" y="193.75" pressure="114" deltaTime="13" /><Packet x="184.75" y="196.25" pressure="118" deltaTime="27" /><Packet x="186.75" y="201.375" pressure="118" deltaTime="107" /><Packet x="186.25" y="198.375" pressure="116" deltaTime="80" /><Packet x="188" y="196" pressure="116" deltaTime="26" /><Packet x="189.625" y="194.75" pressure="116" deltaTime="14" /><Packet x="197.875" y="190.5" pressure="116" deltaTime="40" /><Packet x="203.5" y="188.875" pressure="116" deltaTime="40" /><Packet x="205.25" y="189" pressure="118" deltaTime="40" /><Packet x="205.125" y="189.625" pressure="118" deltaTime="26" /><Packet x="200.125" y="195.25" pressure="120" deltaTime="54" /><Packet x="189.75" y="205.625" pressure="120" deltaTime="93" /><Packet x="196.375" y="202.375" pressure="120" deltaTime="80" /><Packet x="201.5" y="199.25" pressure="120" deltaTime="67" /><Packet x="200.25" y="197.125" pressure="120" deltaTime="66" /><Packet x="193.625" y="177.625" pressure="116" deltaTime="147" /><Packet x="194.25" y="178.875" pressure="116" deltaTime="67" /><Packet x="194.75" y="182.25" pressure="118" deltaTime="40" /><Packet x="194.625" y="189.625" pressure="118" deltaTime="40" /><Packet x="193" y="204.875" pressure="118" deltaTime="40" /><Packet x="191.375" y="212.75" pressure="118" deltaTime="26" /><Packet x="189.125" y="218.625" pressure="118" deltaTime="27" /><Packet x="186.625" y="221.875" pressure="120" deltaTime="27" /><Packet x="184.5" y="223.125" pressure="120" deltaTime="26" /><Packet x="183.375" y="223.125" pressure="120" deltaTime="27" /><Packet x="197.75" y="212.25" pressure="120" deltaTime="133" /><Packet x="198.625" y="210.625" pressure="120" deltaTime="40" /><Packet x="197.125" y="209.25" pressure="120" deltaTime="40" /><Packet x="196.375" y="209.125" pressure="118" deltaTime="27" /><Packet x="201.5" y="218.5" pressure="120" deltaTime="200" /><Packet x="201.5" y="218.375" pressure="120" deltaTime="13" /><Packet x="202.25" y="212.375" pressure="116" deltaTime="54" /><Packet x="202.5" y="206.5" pressure="0" deltaTime="13" /></Stroke><Stroke duration="3333" startSecond="1439305794" startMillisecond="924" lineWidth="1"><Packet x="209.125" y="173.25" pressure="0" deltaTime="0" /><Packet x="209.375" y="172.75" pressure="102" deltaTime="13" /><Packet x="210.25" y="172.5" pressure="112" deltaTime="27" /><Packet x="212.125" y="173.25" pressure="116" deltaTime="26" /><Packet x="215.25" y="178.625" pressure="118" deltaTime="94" /><Packet x="221.125" y="171" pressure="114" deltaTime="66" /><Packet x="223.5" y="168.75" pressure="114" deltaTime="14" /><Packet x="225.25" y="167.625" pressure="114" deltaTime="13" /><Packet x="228.625" y="166.625" pressure="116" deltaTime="27" /><Packet x="230.5" y="166.875" pressure="118" deltaTime="26" /><Packet x="231.25" y="168" pressure="120" deltaTime="40" /><Packet x="230.75" y="169.75" pressure="120" deltaTime="54" /><Packet x="229" y="172.125" pressure="120" deltaTime="26" /><Packet x="227.125" y="174" pressure="120" deltaTime="14" /><Packet x="212.25" y="187.25" pressure="96" deltaTime="53" /><Packet x="206.375" y="193.25" pressure="112" deltaTime="53" /><Packet x="206.625" y="194" pressure="116" deltaTime="27" /><Packet x="208.75" y="196" pressure="118" deltaTime="40" /><Packet x="213" y="203.25" pressure="120" deltaTime="107" /><Packet x="212.625" y="202.625" pressure="122" deltaTime="40" /><Packet x="210.5" y="197.875" pressure="116" deltaTime="40" /><Packet x="210" y="194.375" pressure="116" deltaTime="26" /><Packet x="210.75" y="193" pressure="116" deltaTime="54" /><Packet x="215.125" y="190.625" pressure="118" deltaTime="66" /><Packet x="223.5" y="187.625" pressure="120" deltaTime="54" /><Packet x="228.25" y="186.75" pressure="120" deltaTime="40" /><Packet x="231.875" y="187.375" pressure="120" deltaTime="66" /><Packet x="232.25" y="188.125" pressure="122" deltaTime="40" /><Packet x="232.125" y="189.5" pressure="122" deltaTime="27" /><Packet x="229.375" y="195.375" pressure="122" deltaTime="40" /><Packet x="226.375" y="200" pressure="122" deltaTime="27" /><Packet x="222.75" y="204.375" pressure="122" deltaTime="26" /><Packet x="220.375" y="206.5" pressure="122" deltaTime="27" /><Packet x="218.5" y="207" pressure="122" deltaTime="27" /><Packet x="216.875" y="206.25" pressure="122" deltaTime="26" /><Packet x="210.875" y="199.5" pressure="112" deltaTime="54" /><Packet x="210.125" y="198.25" pressure="112" deltaTime="40" /><Packet x="210.5" y="197.875" pressure="116" deltaTime="40" /><Packet x="213.875" y="196.125" pressure="116" deltaTime="40" /><Packet x="218.25" y="194.875" pressure="118" deltaTime="26" /><Packet x="225.75" y="194.625" pressure="120" deltaTime="67" /><Packet x="222.625" y="197.875" pressure="120" deltaTime="67" /><Packet x="218.375" y="201" pressure="118" deltaTime="26" /><Packet x="216.5" y="202.5" pressure="118" deltaTime="14" /><Packet x="212" y="205.375" pressure="118" deltaTime="66" /><Packet x="218" y="203.25" pressure="120" deltaTime="107" /><Packet x="226.25" y="203.125" pressure="120" deltaTime="67" /><Packet x="226.75" y="203.5" pressure="120" deltaTime="40" /><Packet x="217" y="209" pressure="118" deltaTime="80" /><Packet x="203.25" y="218.375" pressure="120" deltaTime="93" /><Packet x="205.625" y="218.125" pressure="120" deltaTime="40" /><Packet x="216.125" y="215" pressure="120" deltaTime="53" /><Packet x="222.75" y="213.75" pressure="120" deltaTime="27" /><Packet x="228.25" y="213.625" pressure="120" deltaTime="27" /><Packet x="232" y="214.125" pressure="120" deltaTime="53" /><Packet x="230.875" y="213.125" pressure="122" deltaTime="53" /><Packet x="228.75" y="209.25" pressure="122" deltaTime="40" /><Packet x="224.25" y="204" pressure="118" deltaTime="40" /><Packet x="221.125" y="199.25" pressure="118" deltaTime="27" /><Packet x="218.375" y="189.625" pressure="118" deltaTime="227" /><Packet x="219.875" y="204.625" pressure="120" deltaTime="226" /><Packet x="220.375" y="228.75" pressure="122" deltaTime="107" /><Packet x="221.125" y="241.625" pressure="122" deltaTime="53" /><Packet x="220.5" y="257.25" pressure="122" deltaTime="120" /><Packet x="220.375" y="254.5" pressure="122" deltaTime="40" /><Packet x="220.375" y="250.5" pressure="118" deltaTime="14" /><Packet x="220.375" y="242.875" pressure="0" deltaTime="13" /></Stroke></Page></Book>